yplate/__init__.py
yplate/ops.py
yplate/yplate.py
yplate-0.0.1.dist-info/LICENSE
yplate-0.0.1.dist-info/METADATA
yplate-0.0.1.dist-info/WHEEL
yplate-0.0.1.dist-info/entry_points.txt
yplate-0.0.1.dist-info/top_level.txt
yplate-0.0.1.dist-info/RECORD
