Metadata-Version: 2.1
Name: yplate
Version: 0.0.1
Summary: Plate Detection using YOLO v3 powered by OpenCV >=3.x 
Home-page: https://github.com/deepraj1729/yplate
Author: Deepraj Baidya
Author-email: bdeeprajrkm1@gmail.com
License: MIT
Keywords: Detect car/vehicle number plates with ease
Platform: UNKNOWN
Classifier: Programming Language :: Python :: 3
Classifier: License :: OSI Approved :: MIT License
Classifier: Operating System :: OS Independent
Requires-Dist: opencv-python (>=3.4)
Requires-Dist: numpy (>=1.17.4)
